imagespuller/__init__.py
imagespuller/__main__.py
imagespuller/search_image.py
imagespuller-1.0.1.dist-info/METADATA
imagespuller-1.0.1.dist-info/WHEEL
imagespuller-1.0.1.dist-info/top_level.txt
imagespuller-1.0.1.dist-info/RECORD
